{
  "externalControllerServices" : { },
  "flow" : {
    "createdTimestamp" : 1779891454399,
    "description" : "",
    "identifier" : "ingest-queue",
    "lastModifiedTimestamp" : 1779891454399,
    "name" : "ingest-queue",
    "versionCount" : 0
  },
  "flowContents" : {
    "comments" : "",
    "componentType" : "PROCESS_GROUP",
    "connections" : [ {
      "backPressureDataSizeThreshold" : "1 GB",
      "backPressureObjectThreshold" : 10000,
      "bends" : [ {
        "x" : -1728.0,
        "y" : -1736.0
      } ],
      "componentType" : "CONNECTION",
      "destination" : {
        "comments" : "",
        "groupId" : "flow-contents-group",
        "id" : "2511aa86-4cad-3d8c-b416-53ef790dc3f2",
        "name" : "EvaluateJsonPath",
        "type" : "PROCESSOR"
      },
      "flowFileExpiration" : "0 sec",
      "groupIdentifier" : "flow-contents-group",
      "identifier" : "0722ef3f-a067-3b60-8def-0c1f775a1f12",
      "labelIndex" : 0,
      "loadBalanceCompression" : "DO_NOT_COMPRESS",
      "loadBalanceStrategy" : "DO_NOT_LOAD_BALANCE",
      "name" : "",
      "partitioningAttribute" : "",
      "prioritizers" : [ ],
      "selectedRelationships" : [ "success" ],
      "source" : {
        "comments" : "",
        "groupId" : "flow-contents-group",
        "id" : "187abb30-8b20-3995-82a0-3e6518f227ac",
        "name" : "ConsumeAMQP",
        "type" : "PROCESSOR"
      },
      "zIndex" : 16
    }, {
      "backPressureDataSizeThreshold" : "1 GB",
      "backPressureObjectThreshold" : 10000,
      "bends" : [ ],
      "componentType" : "CONNECTION",
      "destination" : {
        "comments" : "",
        "groupId" : "flow-contents-group",
        "id" : "32092143-ca42-359b-a712-7b8499de68c8",
        "name" : "RouteArchives",
        "type" : "PROCESSOR"
      },
      "flowFileExpiration" : "0 sec",
      "groupIdentifier" : "flow-contents-group",
      "identifier" : "1a48420a-d1c4-307e-9b07-061b8eb44444",
      "labelIndex" : 0,
      "loadBalanceCompression" : "DO_NOT_COMPRESS",
      "loadBalanceStrategy" : "DO_NOT_LOAD_BALANCE",
      "name" : "",
      "partitioningAttribute" : "",
      "prioritizers" : [ ],
      "selectedRelationships" : [ "success" ],
      "source" : {
        "comments" : "",
        "groupId" : "flow-contents-group",
        "id" : "448f8746-1683-31f2-9f66-bd46c281a5b1",
        "name" : "FetchS3Object",
        "type" : "PROCESSOR"
      },
      "zIndex" : 18
    }, {
      "backPressureDataSizeThreshold" : "2 GB",
      "backPressureObjectThreshold" : 10000,
      "bends" : [ ],
      "componentType" : "CONNECTION",
      "destination" : {
        "comments" : "",
        "groupId" : "flow-contents-group",
        "id" : "65023eae-019e-1000-4482-1ef840728e48",
        "name" : "RouteFragments",
        "type" : "PROCESSOR"
      },
      "flowFileExpiration" : "0 sec",
      "groupIdentifier" : "flow-contents-group",
      "identifier" : "248ce9b5-c48f-3e8a-bb77-f6f8af924471",
      "labelIndex" : 0,
      "loadBalanceCompression" : "DO_NOT_COMPRESS",
      "loadBalanceStrategy" : "DO_NOT_LOAD_BALANCE",
      "name" : "",
      "partitioningAttribute" : "",
      "prioritizers" : [ ],
      "selectedRelationships" : [ "unmatched" ],
      "source" : {
        "comments" : "",
        "groupId" : "flow-contents-group",
        "id" : "32092143-ca42-359b-a712-7b8499de68c8",
        "name" : "RouteArchives",
        "type" : "PROCESSOR"
      },
      "zIndex" : 8
    }, {
      "backPressureDataSizeThreshold" : "1 GB",
      "backPressureObjectThreshold" : 10000,
      "bends" : [ ],
      "componentType" : "CONNECTION",
      "destination" : {
        "comments" : "",
        "groupId" : "flow-contents-group",
        "id" : "3cc95d62-ad92-3411-bdaf-cf5b04d356bf",
        "name" : "PublishAMQP",
        "type" : "PROCESSOR"
      },
      "flowFileExpiration" : "0 sec",
      "groupIdentifier" : "flow-contents-group",
      "identifier" : "2634153b-14e7-3373-a343-b84c07ab1b3e",
      "labelIndex" : 0,
      "loadBalanceCompression" : "DO_NOT_COMPRESS",
      "loadBalanceStrategy" : "DO_NOT_LOAD_BALANCE",
      "name" : "",
      "partitioningAttribute" : "",
      "prioritizers" : [ ],
      "selectedRelationships" : [ "success" ],
      "source" : {
        "comments" : "",
        "groupId" : "flow-contents-group",
        "id" : "b017df4e-7b42-3a27-93ec-c2a3c1399881",
        "name" : "AttributesToJSON",
        "type" : "PROCESSOR"
      },
      "zIndex" : 14
    }, {
      "backPressureDataSizeThreshold" : "1 GB",
      "backPressureObjectThreshold" : 10000,
      "bends" : [ ],
      "componentType" : "CONNECTION",
      "destination" : {
        "comments" : "",
        "groupId" : "flow-contents-group",
        "id" : "af3f7ddf-719a-380c-bdcf-8e820231bba8",
        "name" : "PutS3Object",
        "type" : "PROCESSOR"
      },
      "flowFileExpiration" : "0 sec",
      "groupIdentifier" : "flow-contents-group",
      "identifier" : "46b7d5d5-c57d-3018-9e1a-681af42e42ab",
      "labelIndex" : 0,
      "loadBalanceCompression" : "DO_NOT_COMPRESS",
      "loadBalanceStrategy" : "DO_NOT_LOAD_BALANCE",
      "name" : "",
      "partitioningAttribute" : "",
      "prioritizers" : [ ],
      "selectedRelationships" : [ "unmatched" ],
      "source" : {
        "comments" : "",
        "groupId" : "flow-contents-group",
        "id" : "65023eae-019e-1000-4482-1ef840728e48",
        "name" : "RouteFragments",
        "type" : "PROCESSOR"
      },
      "zIndex" : 25
    }, {
      "backPressureDataSizeThreshold" : "1 GB",
      "backPressureObjectThreshold" : 10000,
      "bends" : [ ],
      "componentType" : "CONNECTION",
      "destination" : {
        "comments" : "",
        "groupId" : "flow-contents-group",
        "id" : "be34c930-d770-31a7-a25e-ca1b2c2385ab",
        "name" : "UpdateAttribute",
        "type" : "PROCESSOR"
      },
      "flowFileExpiration" : "0 sec",
      "groupIdentifier" : "flow-contents-group",
      "identifier" : "533f1db9-9d99-34bb-9d03-785ba7ddedba",
      "labelIndex" : 0,
      "loadBalanceCompression" : "DO_NOT_COMPRESS",
      "loadBalanceStrategy" : "DO_NOT_LOAD_BALANCE",
      "name" : "",
      "partitioningAttribute" : "",
      "prioritizers" : [ ],
      "selectedRelationships" : [ "matched" ],
      "source" : {
        "comments" : "",
        "groupId" : "flow-contents-group",
        "id" : "2511aa86-4cad-3d8c-b416-53ef790dc3f2",
        "name" : "EvaluateJsonPath",
        "type" : "PROCESSOR"
      },
      "zIndex" : 21
    }, {
      "backPressureDataSizeThreshold" : "1 GB",
      "backPressureObjectThreshold" : 10000,
      "bends" : [ ],
      "componentType" : "CONNECTION",
      "destination" : {
        "groupId" : "2cab6d2f-6895-3797-bc37-f42ab747295a",
        "id" : "3f50a002-4f5d-302a-9834-e0d26243f3b4",
        "name" : "recursive-decomposition-in",
        "type" : "INPUT_PORT"
      },
      "flowFileExpiration" : "0 sec",
      "groupIdentifier" : "flow-contents-group",
      "identifier" : "55822d6c-6103-35c7-aceb-f7a309911152",
      "labelIndex" : 0,
      "loadBalanceCompression" : "DO_NOT_COMPRESS",
      "loadBalanceStrategy" : "DO_NOT_LOAD_BALANCE",
      "name" : "",
      "partitioningAttribute" : "",
      "prioritizers" : [ ],
      "selectedRelationships" : [ "is_archive" ],
      "source" : {
        "comments" : "",
        "groupId" : "flow-contents-group",
        "id" : "32092143-ca42-359b-a712-7b8499de68c8",
        "name" : "RouteArchives",
        "type" : "PROCESSOR"
      },
      "zIndex" : 34
    }, {
      "backPressureDataSizeThreshold" : "100 GB",
      "backPressureObjectThreshold" : 100000,
      "bends" : [ ],
      "componentType" : "CONNECTION",
      "destination" : {
        "groupId" : "3f5fc2ec-9a45-3c49-8a2c-dc15573ea53b",
        "id" : "765588b5-f5d0-38a5-a7d6-f5ad05675583",
        "name" : "recursive-recomposition-in",
        "type" : "INPUT_PORT"
      },
      "flowFileExpiration" : "0 sec",
      "groupIdentifier" : "flow-contents-group",
      "identifier" : "5bed3883-bd29-38d8-9a71-6cf220b6f51f",
      "labelIndex" : 0,
      "loadBalanceCompression" : "DO_NOT_COMPRESS",
      "loadBalanceStrategy" : "DO_NOT_LOAD_BALANCE",
      "name" : "",
      "partitioningAttribute" : "",
      "prioritizers" : [ ],
      "selectedRelationships" : [ "from_archive" ],
      "source" : {
        "comments" : "",
        "groupId" : "flow-contents-group",
        "id" : "65023eae-019e-1000-4482-1ef840728e48",
        "name" : "RouteFragments",
        "type" : "PROCESSOR"
      },
      "zIndex" : 32
    }, {
      "backPressureDataSizeThreshold" : "1 GB",
      "backPressureObjectThreshold" : 10000,
      "bends" : [ ],
      "componentType" : "CONNECTION",
      "destination" : {
        "comments" : "",
        "groupId" : "flow-contents-group",
        "id" : "b017df4e-7b42-3a27-93ec-c2a3c1399881",
        "name" : "AttributesToJSON",
        "type" : "PROCESSOR"
      },
      "flowFileExpiration" : "0 sec",
      "groupIdentifier" : "flow-contents-group",
      "identifier" : "654d7ca3-e7f9-3d74-9c3e-f59d659a3d2b",
      "labelIndex" : 0,
      "loadBalanceCompression" : "DO_NOT_COMPRESS",
      "loadBalanceStrategy" : "DO_NOT_LOAD_BALANCE",
      "name" : "",
      "partitioningAttribute" : "",
      "prioritizers" : [ ],
      "selectedRelationships" : [ "success" ],
      "source" : {
        "comments" : "",
        "groupId" : "flow-contents-group",
        "id" : "d418c468-bfb4-3db9-bccd-2252fae2d832",
        "name" : "UpdateAttribute",
        "type" : "PROCESSOR"
      },
      "zIndex" : 27
    }, {
      "backPressureDataSizeThreshold" : "1 GB",
      "backPressureObjectThreshold" : 10000,
      "bends" : [ ],
      "componentType" : "CONNECTION",
      "destination" : {
        "comments" : "",
        "groupId" : "flow-contents-group",
        "id" : "448f8746-1683-31f2-9f66-bd46c281a5b1",
        "name" : "FetchS3Object",
        "type" : "PROCESSOR"
      },
      "flowFileExpiration" : "0 sec",
      "groupIdentifier" : "flow-contents-group",
      "identifier" : "7221e0eb-27d3-3514-af59-1c2dc0c6a14a",
      "labelIndex" : 0,
      "loadBalanceCompression" : "DO_NOT_COMPRESS",
      "loadBalanceStrategy" : "DO_NOT_LOAD_BALANCE",
      "name" : "",
      "partitioningAttribute" : "",
      "prioritizers" : [ ],
      "selectedRelationships" : [ "success" ],
      "source" : {
        "comments" : "",
        "groupId" : "flow-contents-group",
        "id" : "be34c930-d770-31a7-a25e-ca1b2c2385ab",
        "name" : "UpdateAttribute",
        "type" : "PROCESSOR"
      },
      "zIndex" : 20
    }, {
      "backPressureDataSizeThreshold" : "1 GB",
      "backPressureObjectThreshold" : 10000,
      "bends" : [ ],
      "componentType" : "CONNECTION",
      "destination" : {
        "comments" : "",
        "groupId" : "flow-contents-group",
        "id" : "d418c468-bfb4-3db9-bccd-2252fae2d832",
        "name" : "UpdateAttribute",
        "type" : "PROCESSOR"
      },
      "flowFileExpiration" : "0 sec",
      "groupIdentifier" : "flow-contents-group",
      "identifier" : "79c6bb8c-f648-3cdf-8acb-322f829b8d90",
      "labelIndex" : 0,
      "loadBalanceCompression" : "DO_NOT_COMPRESS",
      "loadBalanceStrategy" : "DO_NOT_LOAD_BALANCE",
      "name" : "",
      "partitioningAttribute" : "",
      "prioritizers" : [ ],
      "selectedRelationships" : [ "success" ],
      "source" : {
        "comments" : "",
        "groupId" : "flow-contents-group",
        "id" : "af3f7ddf-719a-380c-bdcf-8e820231bba8",
        "name" : "PutS3Object",
        "type" : "PROCESSOR"
      },
      "zIndex" : 26
    }, {
      "backPressureDataSizeThreshold" : "1 GB",
      "backPressureObjectThreshold" : 10000,
      "bends" : [ {
        "x" : -1376.0,
        "y" : -616.0
      } ],
      "componentType" : "CONNECTION",
      "destination" : {
        "comments" : "",
        "groupId" : "flow-contents-group",
        "id" : "65023eae-019e-1000-4482-1ef840728e48",
        "name" : "RouteFragments",
        "type" : "PROCESSOR"
      },
      "flowFileExpiration" : "0 sec",
      "groupIdentifier" : "flow-contents-group",
      "identifier" : "834cb30b-2714-3bd8-9f7a-71f36ec05f4f",
      "labelIndex" : 0,
      "loadBalanceCompression" : "DO_NOT_COMPRESS",
      "loadBalanceStrategy" : "DO_NOT_LOAD_BALANCE",
      "name" : "",
      "partitioningAttribute" : "",
      "prioritizers" : [ ],
      "selectedRelationships" : [ "" ],
      "source" : {
        "groupId" : "3f5fc2ec-9a45-3c49-8a2c-dc15573ea53b",
        "id" : "76b77bc4-9234-3e81-b23c-d4353bc20fb3",
        "name" : "recursive-decomposition-out",
        "type" : "OUTPUT_PORT"
      },
      "zIndex" : 36
    }, {
      "backPressureDataSizeThreshold" : "1 GB",
      "backPressureObjectThreshold" : 10000,
      "bends" : [ {
        "x" : -1368.0,
        "y" : -880.0
      } ],
      "componentType" : "CONNECTION",
      "destination" : {
        "comments" : "",
        "groupId" : "flow-contents-group",
        "id" : "32092143-ca42-359b-a712-7b8499de68c8",
        "name" : "RouteArchives",
        "type" : "PROCESSOR"
      },
      "flowFileExpiration" : "0 sec",
      "groupIdentifier" : "flow-contents-group",
      "identifier" : "d02c5863-4a5d-3a63-80c8-8cc07d08fb83",
      "labelIndex" : 0,
      "loadBalanceCompression" : "DO_NOT_COMPRESS",
      "loadBalanceStrategy" : "DO_NOT_LOAD_BALANCE",
      "name" : "",
      "partitioningAttribute" : "",
      "prioritizers" : [ ],
      "selectedRelationships" : [ "" ],
      "source" : {
        "groupId" : "2cab6d2f-6895-3797-bc37-f42ab747295a",
        "id" : "438849b7-3bcd-35f5-a3b2-85b306593f0d",
        "name" : "recursive-decomposition-out",
        "type" : "OUTPUT_PORT"
      },
      "zIndex" : 35
    } ],
    "controllerServices" : [ {
      "bulletinLevel" : "WARN",
      "bundle" : {
        "artifact" : "nifi-aws-nar",
        "group" : "org.apache.nifi",
        "version" : "2.9.0"
      },
      "comments" : "",
      "componentType" : "CONTROLLER_SERVICE",
      "controllerServiceApis" : [ {
        "bundle" : {
          "artifact" : "nifi-aws-service-api-nar",
          "group" : "org.apache.nifi",
          "version" : "2.9.0"
        },
        "type" : "org.apache.nifi.processors.aws.credentials.provider.AwsCredentialsProviderService"
      } ],
      "groupIdentifier" : "flow-contents-group",
      "identifier" : "0e036ef3-a65e-3745-9118-32d973c5e826",
      "name" : "AWSCredentialsProviderControllerService",
      "properties" : {
        "Assume Role STS Region" : "us-west-2",
        "Assume Role Session Time" : "3600",
        "Use Default Credentials" : "false",
        "Use Anonymous Credentials" : "false"
      },
      "propertyDescriptors" : {
        "Assume Role STS Region" : {
          "displayName" : "Assume Role STS Region",
          "dynamic" : false,
          "identifiesControllerService" : false,
          "name" : "Assume Role STS Region",
          "sensitive" : false
        },
        "Assume Role Proxy Configuration Service" : {
          "displayName" : "Assume Role Proxy Configuration Service",
          "dynamic" : false,
          "identifiesControllerService" : true,
          "name" : "Assume Role Proxy Configuration Service",
          "sensitive" : false
        },
        "Access Key ID" : {
          "displayName" : "Access Key ID",
          "dynamic" : false,
          "identifiesControllerService" : false,
          "name" : "Access Key ID",
          "sensitive" : true
        },
        "OAuth2 Access Token Provider" : {
          "displayName" : "OAuth2 Access Token Provider",
          "dynamic" : false,
          "identifiesControllerService" : true,
          "name" : "OAuth2 Access Token Provider",
          "sensitive" : false
        },
        "Assume Role ARN" : {
          "displayName" : "Assume Role ARN",
          "dynamic" : false,
          "identifiesControllerService" : false,
          "name" : "Assume Role ARN",
          "sensitive" : false
        },
        "Assume Role Session Time" : {
          "displayName" : "Assume Role Session Time",
          "dynamic" : false,
          "identifiesControllerService" : false,
          "name" : "Assume Role Session Time",
          "sensitive" : false
        },
        "Assume Role Session Name" : {
          "displayName" : "Assume Role Session Name",
          "dynamic" : false,
          "identifiesControllerService" : false,
          "name" : "Assume Role Session Name",
          "sensitive" : false
        },
        "Use Default Credentials" : {
          "displayName" : "Use Default Credentials",
          "dynamic" : false,
          "identifiesControllerService" : false,
          "name" : "Use Default Credentials",
          "sensitive" : false
        },
        "Assume Role External ID" : {
          "displayName" : "Assume Role External ID",
          "dynamic" : false,
          "identifiesControllerService" : false,
          "name" : "Assume Role External ID",
          "sensitive" : false
        },
        "Assume Role STS Endpoint Override" : {
          "displayName" : "Assume Role STS Endpoint Override",
          "dynamic" : false,
          "identifiesControllerService" : false,
          "name" : "Assume Role STS Endpoint Override",
          "sensitive" : false
        },
        "Profile Name" : {
          "displayName" : "Profile Name",
          "dynamic" : false,
          "identifiesControllerService" : false,
          "name" : "Profile Name",
          "sensitive" : false
        },
        "Credentials File" : {
          "displayName" : "Credentials File",
          "dynamic" : false,
          "identifiesControllerService" : false,
          "name" : "Credentials File",
          "resourceDefinition" : {
            "cardinality" : "SINGLE",
            "resourceTypes" : [ "FILE" ]
          },
          "sensitive" : false
        },
        "Use Anonymous Credentials" : {
          "displayName" : "Use Anonymous Credentials",
          "dynamic" : false,
          "identifiesControllerService" : false,
          "name" : "Use Anonymous Credentials",
          "sensitive" : false
        },
        "Secret Access Key" : {
          "displayName" : "Secret Access Key",
          "dynamic" : false,
          "identifiesControllerService" : false,
          "name" : "Secret Access Key",
          "sensitive" : true
        },
        "Assume Role SSL Context Service" : {
          "displayName" : "Assume Role SSL Context Service",
          "dynamic" : false,
          "identifiesControllerService" : true,
          "name" : "Assume Role SSL Context Service",
          "sensitive" : false
        }
      },
      "scheduledState" : "DISABLED",
      "type" : "org.apache.nifi.processors.aws.credentials.provider.service.AWSCredentialsProviderControllerService"
    } ],
    "defaultBackPressureDataSizeThreshold" : "1 GB",
    "defaultBackPressureObjectThreshold" : 10000,
    "defaultFlowFileExpiration" : "0 sec",
    "executionEngine" : "INHERITED",
    "externalControllerServiceReferences" : { },
    "flowFileConcurrency" : "UNBOUNDED",
    "flowFileOutboundPolicy" : "STREAM_WHEN_AVAILABLE",
    "funnels" : [ ],
    "identifier" : "flow-contents-group",
    "inputPorts" : [ ],
    "labels" : [ ],
    "maxConcurrentTasks" : 1,
    "name" : "ingest-queue",
    "outputPorts" : [ ],
    "position" : {
      "x" : 0.0,
      "y" : 0.0
    },
    "processGroups" : [ {
      "comments" : "",
      "componentType" : "PROCESS_GROUP",
      "connections" : [ ],
      "controllerServices" : [ ],
      "defaultBackPressureDataSizeThreshold" : "1 GB",
      "defaultBackPressureObjectThreshold" : 10000,
      "defaultFlowFileExpiration" : "0 sec",
      "executionEngine" : "INHERITED",
      "flowFileConcurrency" : "UNBOUNDED",
      "flowFileOutboundPolicy" : "STREAM_WHEN_AVAILABLE",
      "funnels" : [ ],
      "groupIdentifier" : "flow-contents-group",
      "identifier" : "2cab6d2f-6895-3797-bc37-f42ab747295a",
      "inputPorts" : [ ],
      "labels" : [ ],
      "maxConcurrentTasks" : 1,
      "name" : "recursive-decomposition",
      "outputPorts" : [ ],
      "position" : {
        "x" : -1192.0,
        "y" : -1088.0
      },
      "processGroups" : [ ],
      "processors" : [ ],
      "remoteProcessGroups" : [ ],
      "scheduledState" : "ENABLED",
      "statelessFlowTimeout" : "1 min",
      "versionedFlowCoordinates" : {
        "branch" : "main",
        "bucketId" : "default",
        "flowId" : "recursive-decomposition",
        "version" : "6baa3943da6ce813449209fbf27a65a135949ffa"
      }
    }, {
      "comments" : "",
      "componentType" : "PROCESS_GROUP",
      "connections" : [ ],
      "controllerServices" : [ ],
      "defaultBackPressureDataSizeThreshold" : "1 GB",
      "defaultBackPressureObjectThreshold" : 10000,
      "defaultFlowFileExpiration" : "0 sec",
      "executionEngine" : "INHERITED",
      "flowFileConcurrency" : "UNBOUNDED",
      "flowFileOutboundPolicy" : "STREAM_WHEN_AVAILABLE",
      "funnels" : [ ],
      "groupIdentifier" : "flow-contents-group",
      "identifier" : "3f5fc2ec-9a45-3c49-8a2c-dc15573ea53b",
      "inputPorts" : [ ],
      "labels" : [ ],
      "maxConcurrentTasks" : 1,
      "name" : "recursive-recomposition",
      "outputPorts" : [ ],
      "position" : {
        "x" : -1200.0,
        "y" : -768.0
      },
      "processGroups" : [ ],
      "processors" : [ ],
      "remoteProcessGroups" : [ ],
      "scheduledState" : "ENABLED",
      "statelessFlowTimeout" : "1 min",
      "versionedFlowCoordinates" : {
        "branch" : "main",
        "bucketId" : "default",
        "flowId" : "recursive-recomposition",
        "storageLocation" : "git@github.com:dustins/nifi-registry.git",
        "version" : "df936130ce05e6915887439559d30d807daf6d3c"
      }
    } ],
    "processors" : [ {
      "autoTerminatedRelationships" : [ ],
      "backoffMechanism" : "PENALIZE_FLOWFILE",
      "bulletinLevel" : "WARN",
      "bundle" : {
        "artifact" : "nifi-amqp-nar",
        "group" : "org.apache.nifi",
        "version" : "2.9.0"
      },
      "comments" : "",
      "componentType" : "PROCESSOR",
      "concurrentlySchedulableTaskCount" : 2,
      "executionNode" : "ALL",
      "groupIdentifier" : "flow-contents-group",
      "identifier" : "187abb30-8b20-3995-82a0-3e6518f227ac",
      "maxBackoffPeriod" : "10 mins",
      "name" : "ConsumeAMQP",
      "penaltyDuration" : "30 sec",
      "position" : {
        "x" : -1904.0,
        "y" : -1912.0
      },
      "properties" : {
        "Max Inbound Message Body Size" : "64 MB",
        "Port" : "5672",
        "Header Key Prefix" : "consume.amqp",
        "Auto-Acknowledge Messages" : "false",
        "Host Name" : "rabbitmq",
        "Prefetch Count" : "0",
        "Header Separator" : ",",
        "AMQP Version" : "0.9.1",
        "Header Output Format" : "Comma-Separated String",
        "Username" : "nifi",
        "Client Certificate Authentication Enabled" : "false",
        "Remove Curly Braces" : "False",
        "Batch Size" : "10",
        "Queue" : "work-queue"
      },
      "propertyDescriptors" : {
        "Max Inbound Message Body Size" : {
          "displayName" : "Max Inbound Message Body Size",
          "dynamic" : false,
          "identifiesControllerService" : false,
          "name" : "Max Inbound Message Body Size",
          "sensitive" : false
        },
        "Port" : {
          "displayName" : "Port",
          "dynamic" : false,
          "identifiesControllerService" : false,
          "name" : "Port",
          "sensitive" : false
        },
        "Brokers" : {
          "displayName" : "Brokers",
          "dynamic" : false,
          "identifiesControllerService" : false,
          "name" : "Brokers",
          "sensitive" : false
        },
        "Header Key Prefix" : {
          "displayName" : "Header Key Prefix",
          "dynamic" : false,
          "identifiesControllerService" : false,
          "name" : "Header Key Prefix",
          "sensitive" : false
        },
        "Auto-Acknowledge Messages" : {
          "displayName" : "Auto-Acknowledge Messages",
          "dynamic" : false,
          "identifiesControllerService" : false,
          "name" : "Auto-Acknowledge Messages",
          "sensitive" : false
        },
        "Host Name" : {
          "displayName" : "Host Name",
          "dynamic" : false,
          "identifiesControllerService" : false,
          "name" : "Host Name",
          "sensitive" : false
        },
        "SSL Context Service" : {
          "displayName" : "SSL Context Service",
          "dynamic" : false,
          "identifiesControllerService" : true,
          "name" : "SSL Context Service",
          "sensitive" : false
        },
        "Prefetch Count" : {
          "displayName" : "Prefetch Count",
          "dynamic" : false,
          "identifiesControllerService" : false,
          "name" : "Prefetch Count",
          "sensitive" : false
        },
        "Header Separator" : {
          "displayName" : "Header Separator",
          "dynamic" : false,
          "identifiesControllerService" : false,
          "name" : "Header Separator",
          "sensitive" : false
        },
        "AMQP Version" : {
          "displayName" : "AMQP Version",
          "dynamic" : false,
          "identifiesControllerService" : false,
          "name" : "AMQP Version",
          "sensitive" : false
        },
        "Header Output Format" : {
          "displayName" : "Header Output Format",
          "dynamic" : false,
          "identifiesControllerService" : false,
          "name" : "Header Output Format",
          "sensitive" : false
        },
        "Virtual Host" : {
          "displayName" : "Virtual Host",
          "dynamic" : false,
          "identifiesControllerService" : false,
          "name" : "Virtual Host",
          "sensitive" : false
        },
        "Username" : {
          "displayName" : "Username",
          "dynamic" : false,
          "identifiesControllerService" : false,
          "name" : "Username",
          "sensitive" : false
        },
        "Client Certificate Authentication Enabled" : {
          "displayName" : "Client Certificate Authentication Enabled",
          "dynamic" : false,
          "identifiesControllerService" : false,
          "name" : "Client Certificate Authentication Enabled",
          "sensitive" : false
        },
        "Remove Curly Braces" : {
          "displayName" : "Remove Curly Braces",
          "dynamic" : false,
          "identifiesControllerService" : false,
          "name" : "Remove Curly Braces",
          "sensitive" : false
        },
        "Batch Size" : {
          "displayName" : "Batch Size",
          "dynamic" : false,
          "identifiesControllerService" : false,
          "name" : "Batch Size",
          "sensitive" : false
        },
        "Queue" : {
          "displayName" : "Queue",
          "dynamic" : false,
          "identifiesControllerService" : false,
          "name" : "Queue",
          "sensitive" : false
        },
        "Password" : {
          "displayName" : "Password",
          "dynamic" : false,
          "identifiesControllerService" : false,
          "name" : "Password",
          "sensitive" : true
        }
      },
      "retriedRelationships" : [ ],
      "retryCount" : 10,
      "runDurationMillis" : 0,
      "scheduledState" : "ENABLED",
      "schedulingPeriod" : "0 sec",
      "schedulingStrategy" : "TIMER_DRIVEN",
      "style" : { },
      "type" : "org.apache.nifi.amqp.processors.ConsumeAMQP",
      "yieldDuration" : "1 sec"
    }, {
      "autoTerminatedRelationships" : [ "failure", "unmatched" ],
      "backoffMechanism" : "PENALIZE_FLOWFILE",
      "bulletinLevel" : "WARN",
      "bundle" : {
        "artifact" : "nifi-standard-nar",
        "group" : "org.apache.nifi",
        "version" : "2.9.0"
      },
      "comments" : "",
      "componentType" : "PROCESSOR",
      "concurrentlySchedulableTaskCount" : 2,
      "executionNode" : "ALL",
      "groupIdentifier" : "flow-contents-group",
      "identifier" : "2511aa86-4cad-3d8c-b416-53ef790dc3f2",
      "maxBackoffPeriod" : "10 mins",
      "name" : "EvaluateJsonPath",
      "penaltyDuration" : "30 sec",
      "position" : {
        "x" : -1896.0,
        "y" : -1688.0
      },
      "properties" : {
        "Destination" : "flowfile-attribute",
        "Max String Length" : "20 MB",
        "file.group" : "$[\"file.group\"]",
        "file.lastModifiedTime" : "$[\"file.lastModifiedTime\"]",
        "Return Type" : "auto-detect",
        "original.uuid" : "$.uuid",
        "Null Value Representation" : "empty string",
        "mime.type" : "$[\"mime.type\"]",
        "file.size" : "$[\"file.size\"]",
        "mime.charset" : "$[\"mime.charset\"]",
        "file.permissions" : "$[\"file.permissions\"]",
        "uuid" : "$.uuid",
        "Path Not Found Behavior" : "ignore",
        "trace.start" : "$[\"trace.start\"]",
        "path" : "$.path",
        "filename" : "$.filename",
        "flow.source" : "$[\"flow.source\"]",
        "file.owner" : "$[\"file.owner\"]",
        "mime.extension" : "$[\"mime.extension\"]"
      },
      "propertyDescriptors" : {
        "Destination" : {
          "displayName" : "Destination",
          "dynamic" : false,
          "identifiesControllerService" : false,
          "name" : "Destination",
          "sensitive" : false
        },
        "Max String Length" : {
          "displayName" : "Max String Length",
          "dynamic" : false,
          "identifiesControllerService" : false,
          "name" : "Max String Length",
          "sensitive" : false
        },
        "file.group" : {
          "displayName" : "file.group",
          "dynamic" : true,
          "identifiesControllerService" : false,
          "name" : "file.group",
          "sensitive" : false
        },
        "file.lastModifiedTime" : {
          "displayName" : "file.lastModifiedTime",
          "dynamic" : true,
          "identifiesControllerService" : false,
          "name" : "file.lastModifiedTime",
          "sensitive" : false
        },
        "Return Type" : {
          "displayName" : "Return Type",
          "dynamic" : false,
          "identifiesControllerService" : false,
          "name" : "Return Type",
          "sensitive" : false
        },
        "original.uuid" : {
          "displayName" : "original.uuid",
          "dynamic" : true,
          "identifiesControllerService" : false,
          "name" : "original.uuid",
          "sensitive" : false
        },
        "Null Value Representation" : {
          "displayName" : "Null Value Representation",
          "dynamic" : false,
          "identifiesControllerService" : false,
          "name" : "Null Value Representation",
          "sensitive" : false
        },
        "mime.type" : {
          "displayName" : "mime.type",
          "dynamic" : true,
          "identifiesControllerService" : false,
          "name" : "mime.type",
          "sensitive" : false
        },
        "file.size" : {
          "displayName" : "file.size",
          "dynamic" : true,
          "identifiesControllerService" : false,
          "name" : "file.size",
          "sensitive" : false
        },
        "mime.charset" : {
          "displayName" : "mime.charset",
          "dynamic" : true,
          "identifiesControllerService" : false,
          "name" : "mime.charset",
          "sensitive" : false
        },
        "file.permissions" : {
          "displayName" : "file.permissions",
          "dynamic" : true,
          "identifiesControllerService" : false,
          "name" : "file.permissions",
          "sensitive" : false
        },
        "uuid" : {
          "displayName" : "uuid",
          "dynamic" : true,
          "identifiesControllerService" : false,
          "name" : "uuid",
          "sensitive" : false
        },
        "Path Not Found Behavior" : {
          "displayName" : "Path Not Found Behavior",
          "dynamic" : false,
          "identifiesControllerService" : false,
          "name" : "Path Not Found Behavior",
          "sensitive" : false
        },
        "trace.start" : {
          "displayName" : "trace.start",
          "dynamic" : true,
          "identifiesControllerService" : false,
          "name" : "trace.start",
          "sensitive" : false
        },
        "path" : {
          "displayName" : "path",
          "dynamic" : true,
          "identifiesControllerService" : false,
          "name" : "path",
          "sensitive" : false
        },
        "filename" : {
          "displayName" : "filename",
          "dynamic" : true,
          "identifiesControllerService" : false,
          "name" : "filename",
          "sensitive" : false
        },
        "flow.source" : {
          "displayName" : "flow.source",
          "dynamic" : true,
          "identifiesControllerService" : false,
          "name" : "flow.source",
          "sensitive" : false
        },
        "file.owner" : {
          "displayName" : "file.owner",
          "dynamic" : true,
          "identifiesControllerService" : false,
          "name" : "file.owner",
          "sensitive" : false
        },
        "mime.extension" : {
          "displayName" : "mime.extension",
          "dynamic" : true,
          "identifiesControllerService" : false,
          "name" : "mime.extension",
          "sensitive" : false
        }
      },
      "retriedRelationships" : [ ],
      "retryCount" : 10,
      "runDurationMillis" : 1000,
      "scheduledState" : "ENABLED",
      "schedulingPeriod" : "0 sec",
      "schedulingStrategy" : "TIMER_DRIVEN",
      "style" : { },
      "type" : "org.apache.nifi.processors.standard.EvaluateJsonPath",
      "yieldDuration" : "1 sec"
    }, {
      "autoTerminatedRelationships" : [ ],
      "backoffMechanism" : "PENALIZE_FLOWFILE",
      "bulletinLevel" : "WARN",
      "bundle" : {
        "artifact" : "nifi-standard-nar",
        "group" : "org.apache.nifi",
        "version" : "2.9.0"
      },
      "comments" : "",
      "componentType" : "PROCESSOR",
      "concurrentlySchedulableTaskCount" : 4,
      "executionNode" : "ALL",
      "groupIdentifier" : "flow-contents-group",
      "identifier" : "32092143-ca42-359b-a712-7b8499de68c8",
      "maxBackoffPeriod" : "10 mins",
      "name" : "RouteArchives",
      "penaltyDuration" : "30 sec",
      "position" : {
        "x" : -1896.0,
        "y" : -1008.0
      },
      "properties" : {
        "Routing Strategy" : "Route to Property name",
        "is_archive" : "${mime.type:matches('application/x-tar|application/zip|application/gzip')}"
      },
      "propertyDescriptors" : {
        "Routing Strategy" : {
          "displayName" : "Routing Strategy",
          "dynamic" : false,
          "identifiesControllerService" : false,
          "name" : "Routing Strategy",
          "sensitive" : false
        },
        "is_archive" : {
          "displayName" : "is_archive",
          "dynamic" : true,
          "identifiesControllerService" : false,
          "name" : "is_archive",
          "sensitive" : false
        }
      },
      "retriedRelationships" : [ ],
      "retryCount" : 10,
      "runDurationMillis" : 1000,
      "scheduledState" : "ENABLED",
      "schedulingPeriod" : "0 sec",
      "schedulingStrategy" : "TIMER_DRIVEN",
      "style" : { },
      "type" : "org.apache.nifi.processors.standard.RouteOnAttribute",
      "yieldDuration" : "1 sec"
    }, {
      "autoTerminatedRelationships" : [ "failure", "success" ],
      "backoffMechanism" : "PENALIZE_FLOWFILE",
      "bulletinLevel" : "WARN",
      "bundle" : {
        "artifact" : "nifi-amqp-nar",
        "group" : "org.apache.nifi",
        "version" : "2.9.0"
      },
      "comments" : "",
      "componentType" : "PROCESSOR",
      "concurrentlySchedulableTaskCount" : 1,
      "executionNode" : "ALL",
      "groupIdentifier" : "flow-contents-group",
      "identifier" : "3cc95d62-ad92-3411-bdaf-cf5b04d356bf",
      "maxBackoffPeriod" : "10 mins",
      "name" : "PublishAMQP",
      "penaltyDuration" : "30 sec",
      "position" : {
        "x" : -1912.0,
        "y" : 80.0
      },
      "properties" : {
        "Routing Key" : "output-queue",
        "Exchange Name" : "",
        "Port" : "5672",
        "Host Name" : "rabbitmq",
        "Header Separator" : ",",
        "AMQP Version" : "0.9.1",
        "Username" : "nifi",
        "Client Certificate Authentication Enabled" : "false",
        "Headers Source" : "AMQP_HEADERS_ATTRIBUTE"
      },
      "propertyDescriptors" : {
        "Routing Key" : {
          "displayName" : "Routing Key",
          "dynamic" : false,
          "identifiesControllerService" : false,
          "name" : "Routing Key",
          "sensitive" : false
        },
        "Exchange Name" : {
          "displayName" : "Exchange Name",
          "dynamic" : false,
          "identifiesControllerService" : false,
          "name" : "Exchange Name",
          "sensitive" : false
        },
        "Port" : {
          "displayName" : "Port",
          "dynamic" : false,
          "identifiesControllerService" : false,
          "name" : "Port",
          "sensitive" : false
        },
        "Brokers" : {
          "displayName" : "Brokers",
          "dynamic" : false,
          "identifiesControllerService" : false,
          "name" : "Brokers",
          "sensitive" : false
        },
        "Host Name" : {
          "displayName" : "Host Name",
          "dynamic" : false,
          "identifiesControllerService" : false,
          "name" : "Host Name",
          "sensitive" : false
        },
        "Headers Pattern" : {
          "displayName" : "Headers Pattern",
          "dynamic" : false,
          "identifiesControllerService" : false,
          "name" : "Headers Pattern",
          "sensitive" : false
        },
        "SSL Context Service" : {
          "displayName" : "SSL Context Service",
          "dynamic" : false,
          "identifiesControllerService" : true,
          "name" : "SSL Context Service",
          "sensitive" : false
        },
        "Header Separator" : {
          "displayName" : "Header Separator",
          "dynamic" : false,
          "identifiesControllerService" : false,
          "name" : "Header Separator",
          "sensitive" : false
        },
        "AMQP Version" : {
          "displayName" : "AMQP Version",
          "dynamic" : false,
          "identifiesControllerService" : false,
          "name" : "AMQP Version",
          "sensitive" : false
        },
        "Virtual Host" : {
          "displayName" : "Virtual Host",
          "dynamic" : false,
          "identifiesControllerService" : false,
          "name" : "Virtual Host",
          "sensitive" : false
        },
        "Username" : {
          "displayName" : "Username",
          "dynamic" : false,
          "identifiesControllerService" : false,
          "name" : "Username",
          "sensitive" : false
        },
        "Client Certificate Authentication Enabled" : {
          "displayName" : "Client Certificate Authentication Enabled",
          "dynamic" : false,
          "identifiesControllerService" : false,
          "name" : "Client Certificate Authentication Enabled",
          "sensitive" : false
        },
        "Headers Source" : {
          "displayName" : "Headers Source",
          "dynamic" : false,
          "identifiesControllerService" : false,
          "name" : "Headers Source",
          "sensitive" : false
        },
        "Password" : {
          "displayName" : "Password",
          "dynamic" : false,
          "identifiesControllerService" : false,
          "name" : "Password",
          "sensitive" : true
        }
      },
      "retriedRelationships" : [ ],
      "retryCount" : 10,
      "runDurationMillis" : 0,
      "scheduledState" : "ENABLED",
      "schedulingPeriod" : "0 sec",
      "schedulingStrategy" : "TIMER_DRIVEN",
      "style" : { },
      "type" : "org.apache.nifi.amqp.processors.PublishAMQP",
      "yieldDuration" : "1 sec"
    }, {
      "autoTerminatedRelationships" : [ "failure" ],
      "backoffMechanism" : "PENALIZE_FLOWFILE",
      "bulletinLevel" : "WARN",
      "bundle" : {
        "artifact" : "nifi-aws-nar",
        "group" : "org.apache.nifi",
        "version" : "2.9.0"
      },
      "comments" : "",
      "componentType" : "PROCESSOR",
      "concurrentlySchedulableTaskCount" : 8,
      "executionNode" : "ALL",
      "groupIdentifier" : "flow-contents-group",
      "identifier" : "448f8746-1683-31f2-9f66-bd46c281a5b1",
      "maxBackoffPeriod" : "10 mins",
      "name" : "FetchS3Object",
      "penaltyDuration" : "30 sec",
      "position" : {
        "x" : -1896.0,
        "y" : -1240.0
      },
      "properties" : {
        "Endpoint Override URL" : "https://garage-api.swigg.net",
        "Object Key" : "${original.uuid}",
        "Bucket" : "work-queue",
        "AWS Credentials Provider Service" : "0e036ef3-a65e-3745-9118-32d973c5e826",
        "Communications Timeout" : "30 secs",
        "Region" : "use-custom-region",
        "Custom Region" : "garage",
        "Requester Pays" : "false"
      },
      "propertyDescriptors" : {
        "Endpoint Override URL" : {
          "displayName" : "Endpoint Override URL",
          "dynamic" : false,
          "identifiesControllerService" : false,
          "name" : "Endpoint Override URL",
          "sensitive" : false
        },
        "Object Key" : {
          "displayName" : "Object Key",
          "dynamic" : false,
          "identifiesControllerService" : false,
          "name" : "Object Key",
          "sensitive" : false
        },
        "Proxy Configuration Service" : {
          "displayName" : "Proxy Configuration Service",
          "dynamic" : false,
          "identifiesControllerService" : true,
          "name" : "Proxy Configuration Service",
          "sensitive" : false
        },
        "Range Start" : {
          "displayName" : "Range Start",
          "dynamic" : false,
          "identifiesControllerService" : false,
          "name" : "Range Start",
          "sensitive" : false
        },
        "SSL Context Service" : {
          "displayName" : "SSL Context Service",
          "dynamic" : false,
          "identifiesControllerService" : true,
          "name" : "SSL Context Service",
          "sensitive" : false
        },
        "Bucket" : {
          "displayName" : "Bucket",
          "dynamic" : false,
          "identifiesControllerService" : false,
          "name" : "Bucket",
          "sensitive" : false
        },
        "Version" : {
          "displayName" : "Version",
          "dynamic" : false,
          "identifiesControllerService" : false,
          "name" : "Version",
          "sensitive" : false
        },
        "AWS Credentials Provider Service" : {
          "displayName" : "AWS Credentials Provider Service",
          "dynamic" : false,
          "identifiesControllerService" : true,
          "name" : "AWS Credentials Provider Service",
          "sensitive" : false
        },
        "Communications Timeout" : {
          "displayName" : "Communications Timeout",
          "dynamic" : false,
          "identifiesControllerService" : false,
          "name" : "Communications Timeout",
          "sensitive" : false
        },
        "Region" : {
          "displayName" : "Region",
          "dynamic" : false,
          "identifiesControllerService" : false,
          "name" : "Region",
          "sensitive" : false
        },
        "Encryption Service" : {
          "displayName" : "Encryption Service",
          "dynamic" : false,
          "identifiesControllerService" : true,
          "name" : "Encryption Service",
          "sensitive" : false
        },
        "Custom Region" : {
          "displayName" : "Custom Region",
          "dynamic" : false,
          "identifiesControllerService" : false,
          "name" : "Custom Region",
          "sensitive" : false
        },
        "Requester Pays" : {
          "displayName" : "Requester Pays",
          "dynamic" : false,
          "identifiesControllerService" : false,
          "name" : "Requester Pays",
          "sensitive" : false
        },
        "Range Length" : {
          "displayName" : "Range Length",
          "dynamic" : false,
          "identifiesControllerService" : false,
          "name" : "Range Length",
          "sensitive" : false
        }
      },
      "retriedRelationships" : [ "failure" ],
      "retryCount" : 10,
      "runDurationMillis" : 0,
      "scheduledState" : "ENABLED",
      "schedulingPeriod" : "0 sec",
      "schedulingStrategy" : "TIMER_DRIVEN",
      "style" : { },
      "type" : "org.apache.nifi.processors.aws.s3.FetchS3Object",
      "yieldDuration" : "1 sec"
    }, {
      "autoTerminatedRelationships" : [ ],
      "backoffMechanism" : "PENALIZE_FLOWFILE",
      "bulletinLevel" : "WARN",
      "bundle" : {
        "artifact" : "nifi-standard-nar",
        "group" : "org.apache.nifi",
        "version" : "2.9.0"
      },
      "comments" : "",
      "componentType" : "PROCESSOR",
      "concurrentlySchedulableTaskCount" : 4,
      "executionNode" : "ALL",
      "groupIdentifier" : "flow-contents-group",
      "identifier" : "65023eae-019e-1000-4482-1ef840728e48",
      "maxBackoffPeriod" : "10 mins",
      "name" : "RouteFragments",
      "penaltyDuration" : "30 sec",
      "position" : {
        "x" : -1904.0,
        "y" : -800.0
      },
      "properties" : {
        "Routing Strategy" : "Route to Property name",
        "from_archive" : "${archive.lineage.fragment.identifier:substringAfterLast(':|:'):isEmpty():equals('false'):or(${fragment.identifier:isEmpty():equals('false')})}"
      },
      "propertyDescriptors" : {
        "Routing Strategy" : {
          "displayName" : "Routing Strategy",
          "dynamic" : false,
          "identifiesControllerService" : false,
          "name" : "Routing Strategy",
          "sensitive" : false
        },
        "from_archive" : {
          "displayName" : "from_archive",
          "dynamic" : true,
          "identifiesControllerService" : false,
          "name" : "from_archive",
          "sensitive" : false
        }
      },
      "retriedRelationships" : [ ],
      "retryCount" : 10,
      "runDurationMillis" : 1000,
      "scheduledState" : "ENABLED",
      "schedulingPeriod" : "0 sec",
      "schedulingStrategy" : "TIMER_DRIVEN",
      "style" : { },
      "type" : "org.apache.nifi.processors.standard.RouteOnAttribute",
      "yieldDuration" : "1 sec"
    }, {
      "autoTerminatedRelationships" : [ "failure" ],
      "backoffMechanism" : "PENALIZE_FLOWFILE",
      "bulletinLevel" : "WARN",
      "bundle" : {
        "artifact" : "nifi-aws-nar",
        "group" : "org.apache.nifi",
        "version" : "2.9.0"
      },
      "comments" : "",
      "componentType" : "PROCESSOR",
      "concurrentlySchedulableTaskCount" : 1,
      "executionNode" : "ALL",
      "groupIdentifier" : "flow-contents-group",
      "identifier" : "af3f7ddf-719a-380c-bdcf-8e820231bba8",
      "maxBackoffPeriod" : "10 mins",
      "name" : "PutS3Object",
      "penaltyDuration" : "30 sec",
      "position" : {
        "x" : -1904.0,
        "y" : -536.0
      },
      "properties" : {
        "FullControl User List" : "${s3.permissions.full.users}",
        "Resource Transfer Source" : "FLOWFILE_CONTENT",
        "Endpoint Override URL" : "https://garage-api.swigg.net",
        "Multipart Upload Max Age Threshold" : "7 days",
        "Canned ACL" : "${s3.permissions.cannedacl}",
        "Use Path Style Access" : "true",
        "Write ACL User List" : "${s3.permissions.writeacl.users}",
        "Use Chunked Encoding" : "true",
        "Read ACL User List" : "${s3.permissions.readacl.users}",
        "Storage Class" : "STANDARD",
        "Multipart Part Size" : "5 GB",
        "Remove Tag Prefix" : "false",
        "Object Key" : "${original.uuid}",
        "Multipart Threshold" : "5 GB",
        "Temporary Directory Multipart State" : "${java.io.tmpdir}",
        "Bucket" : "output-queue",
        "Multipart Upload AgeOff Interval" : "60 min",
        "AWS Credentials Provider Service" : "0e036ef3-a65e-3745-9118-32d973c5e826",
        "Communications Timeout" : "30 secs",
        "Region" : "use-custom-region",
        "Read Permission User List" : "${s3.permissions.read.users}",
        "Custom Region" : "garage"
      },
      "propertyDescriptors" : {
        "FullControl User List" : {
          "displayName" : "FullControl User List",
          "dynamic" : false,
          "identifiesControllerService" : false,
          "name" : "FullControl User List",
          "sensitive" : false
        },
        "Resource Transfer Source" : {
          "displayName" : "Resource Transfer Source",
          "dynamic" : false,
          "identifiesControllerService" : false,
          "name" : "Resource Transfer Source",
          "sensitive" : false
        },
        "Cache Control" : {
          "displayName" : "Cache Control",
          "dynamic" : false,
          "identifiesControllerService" : false,
          "name" : "Cache Control",
          "sensitive" : false
        },
        "Endpoint Override URL" : {
          "displayName" : "Endpoint Override URL",
          "dynamic" : false,
          "identifiesControllerService" : false,
          "name" : "Endpoint Override URL",
          "sensitive" : false
        },
        "File Resource Service" : {
          "displayName" : "File Resource Service",
          "dynamic" : false,
          "identifiesControllerService" : true,
          "name" : "File Resource Service",
          "sensitive" : false
        },
        "Multipart Upload Max Age Threshold" : {
          "displayName" : "Multipart Upload Max Age Threshold",
          "dynamic" : false,
          "identifiesControllerService" : false,
          "name" : "Multipart Upload Max Age Threshold",
          "sensitive" : false
        },
        "Proxy Configuration Service" : {
          "displayName" : "Proxy Configuration Service",
          "dynamic" : false,
          "identifiesControllerService" : true,
          "name" : "Proxy Configuration Service",
          "sensitive" : false
        },
        "Object Tags Prefix" : {
          "displayName" : "Object Tags Prefix",
          "dynamic" : false,
          "identifiesControllerService" : false,
          "name" : "Object Tags Prefix",
          "sensitive" : false
        },
        "Content Type" : {
          "displayName" : "Content Type",
          "dynamic" : false,
          "identifiesControllerService" : false,
          "name" : "Content Type",
          "sensitive" : false
        },
        "Canned ACL" : {
          "displayName" : "Canned ACL",
          "dynamic" : false,
          "identifiesControllerService" : false,
          "name" : "Canned ACL",
          "sensitive" : false
        },
        "Use Path Style Access" : {
          "displayName" : "Use Path Style Access",
          "dynamic" : false,
          "identifiesControllerService" : false,
          "name" : "Use Path Style Access",
          "sensitive" : false
        },
        "Encryption Service" : {
          "displayName" : "Encryption Service",
          "dynamic" : false,
          "identifiesControllerService" : true,
          "name" : "Encryption Service",
          "sensitive" : false
        },
        "Write ACL User List" : {
          "displayName" : "Write ACL User List",
          "dynamic" : false,
          "identifiesControllerService" : false,
          "name" : "Write ACL User List",
          "sensitive" : false
        },
        "Use Chunked Encoding" : {
          "displayName" : "Use Chunked Encoding",
          "dynamic" : false,
          "identifiesControllerService" : false,
          "name" : "Use Chunked Encoding",
          "sensitive" : false
        },
        "Read ACL User List" : {
          "displayName" : "Read ACL User List",
          "dynamic" : false,
          "identifiesControllerService" : false,
          "name" : "Read ACL User List",
          "sensitive" : false
        },
        "Content Disposition" : {
          "displayName" : "Content Disposition",
          "dynamic" : false,
          "identifiesControllerService" : false,
          "name" : "Content Disposition",
          "sensitive" : false
        },
        "Storage Class" : {
          "displayName" : "Storage Class",
          "dynamic" : false,
          "identifiesControllerService" : false,
          "name" : "Storage Class",
          "sensitive" : false
        },
        "Multipart Part Size" : {
          "displayName" : "Multipart Part Size",
          "dynamic" : false,
          "identifiesControllerService" : false,
          "name" : "Multipart Part Size",
          "sensitive" : false
        },
        "Remove Tag Prefix" : {
          "displayName" : "Remove Tag Prefix",
          "dynamic" : false,
          "identifiesControllerService" : false,
          "name" : "Remove Tag Prefix",
          "sensitive" : false
        },
        "Object Key" : {
          "displayName" : "Object Key",
          "dynamic" : false,
          "identifiesControllerService" : false,
          "name" : "Object Key",
          "sensitive" : false
        },
        "Multipart Threshold" : {
          "displayName" : "Multipart Threshold",
          "dynamic" : false,
          "identifiesControllerService" : false,
          "name" : "Multipart Threshold",
          "sensitive" : false
        },
        "Temporary Directory Multipart State" : {
          "displayName" : "Temporary Directory Multipart State",
          "dynamic" : false,
          "identifiesControllerService" : false,
          "name" : "Temporary Directory Multipart State",
          "sensitive" : false
        },
        "SSL Context Service" : {
          "displayName" : "SSL Context Service",
          "dynamic" : false,
          "identifiesControllerService" : true,
          "name" : "SSL Context Service",
          "sensitive" : false
        },
        "Bucket" : {
          "displayName" : "Bucket",
          "dynamic" : false,
          "identifiesControllerService" : false,
          "name" : "Bucket",
          "sensitive" : false
        },
        "Multipart Upload AgeOff Interval" : {
          "displayName" : "Multipart Upload AgeOff Interval",
          "dynamic" : false,
          "identifiesControllerService" : false,
          "name" : "Multipart Upload AgeOff Interval",
          "sensitive" : false
        },
        "AWS Credentials Provider Service" : {
          "displayName" : "AWS Credentials Provider Service",
          "dynamic" : false,
          "identifiesControllerService" : true,
          "name" : "AWS Credentials Provider Service",
          "sensitive" : false
        },
        "Communications Timeout" : {
          "displayName" : "Communications Timeout",
          "dynamic" : false,
          "identifiesControllerService" : false,
          "name" : "Communications Timeout",
          "sensitive" : false
        },
        "Region" : {
          "displayName" : "Region",
          "dynamic" : false,
          "identifiesControllerService" : false,
          "name" : "Region",
          "sensitive" : false
        },
        "Read Permission User List" : {
          "displayName" : "Read Permission User List",
          "dynamic" : false,
          "identifiesControllerService" : false,
          "name" : "Read Permission User List",
          "sensitive" : false
        },
        "Custom Region" : {
          "displayName" : "Custom Region",
          "dynamic" : false,
          "identifiesControllerService" : false,
          "name" : "Custom Region",
          "sensitive" : false
        }
      },
      "retriedRelationships" : [ ],
      "retryCount" : 10,
      "runDurationMillis" : 0,
      "scheduledState" : "ENABLED",
      "schedulingPeriod" : "0 sec",
      "schedulingStrategy" : "TIMER_DRIVEN",
      "style" : { },
      "type" : "org.apache.nifi.processors.aws.s3.PutS3Object",
      "yieldDuration" : "1 sec"
    }, {
      "autoTerminatedRelationships" : [ "failure" ],
      "backoffMechanism" : "PENALIZE_FLOWFILE",
      "bulletinLevel" : "WARN",
      "bundle" : {
        "artifact" : "nifi-standard-nar",
        "group" : "org.apache.nifi",
        "version" : "2.9.0"
      },
      "comments" : "",
      "componentType" : "PROCESSOR",
      "concurrentlySchedulableTaskCount" : 1,
      "executionNode" : "ALL",
      "groupIdentifier" : "flow-contents-group",
      "identifier" : "b017df4e-7b42-3a27-93ec-c2a3c1399881",
      "maxBackoffPeriod" : "10 mins",
      "name" : "AttributesToJSON",
      "penaltyDuration" : "30 sec",
      "position" : {
        "x" : -1912.0,
        "y" : -120.0
      },
      "properties" : {
        "Destination" : "flowfile-content",
        "Null Value" : "false",
        "Pretty Print" : "true",
        "Include Core Attributes" : "true",
        "JSON Handling Strategy" : "ESCAPED"
      },
      "propertyDescriptors" : {
        "Attributes Regular Expression" : {
          "displayName" : "Attributes Regular Expression",
          "dynamic" : false,
          "identifiesControllerService" : false,
          "name" : "Attributes Regular Expression",
          "sensitive" : false
        },
        "Destination" : {
          "displayName" : "Destination",
          "dynamic" : false,
          "identifiesControllerService" : false,
          "name" : "Destination",
          "sensitive" : false
        },
        "Null Value" : {
          "displayName" : "Null Value",
          "dynamic" : false,
          "identifiesControllerService" : false,
          "name" : "Null Value",
          "sensitive" : false
        },
        "Attributes List" : {
          "displayName" : "Attributes List",
          "dynamic" : false,
          "identifiesControllerService" : false,
          "name" : "Attributes List",
          "sensitive" : false
        },
        "Pretty Print" : {
          "displayName" : "Pretty Print",
          "dynamic" : false,
          "identifiesControllerService" : false,
          "name" : "Pretty Print",
          "sensitive" : false
        },
        "Include Core Attributes" : {
          "displayName" : "Include Core Attributes",
          "dynamic" : false,
          "identifiesControllerService" : false,
          "name" : "Include Core Attributes",
          "sensitive" : false
        },
        "JSON Handling Strategy" : {
          "displayName" : "JSON Handling Strategy",
          "dynamic" : false,
          "identifiesControllerService" : false,
          "name" : "JSON Handling Strategy",
          "sensitive" : false
        }
      },
      "retriedRelationships" : [ ],
      "retryCount" : 10,
      "runDurationMillis" : 0,
      "scheduledState" : "ENABLED",
      "schedulingPeriod" : "0 sec",
      "schedulingStrategy" : "TIMER_DRIVEN",
      "style" : { },
      "type" : "org.apache.nifi.processors.standard.AttributesToJSON",
      "yieldDuration" : "1 sec"
    }, {
      "autoTerminatedRelationships" : [ ],
      "backoffMechanism" : "PENALIZE_FLOWFILE",
      "bulletinLevel" : "WARN",
      "bundle" : {
        "artifact" : "nifi-update-attribute-nar",
        "group" : "org.apache.nifi",
        "version" : "2.9.0"
      },
      "comments" : "",
      "componentType" : "PROCESSOR",
      "concurrentlySchedulableTaskCount" : 2,
      "executionNode" : "ALL",
      "groupIdentifier" : "flow-contents-group",
      "identifier" : "be34c930-d770-31a7-a25e-ca1b2c2385ab",
      "maxBackoffPeriod" : "10 mins",
      "name" : "UpdateAttribute",
      "penaltyDuration" : "30 sec",
      "position" : {
        "x" : -1896.0,
        "y" : -1464.0
      },
      "properties" : {
        "Store State" : "Do not store state",
        "Cache Value Lookup Cache Size" : "100",
        "uuid" : "$[\"original.uuid\"]"
      },
      "propertyDescriptors" : {
        "Delete Attributes Expression" : {
          "displayName" : "Delete Attributes Expression",
          "dynamic" : false,
          "identifiesControllerService" : false,
          "name" : "Delete Attributes Expression",
          "sensitive" : false
        },
        "Store State" : {
          "displayName" : "Store State",
          "dynamic" : false,
          "identifiesControllerService" : false,
          "name" : "Store State",
          "sensitive" : false
        },
        "Cache Value Lookup Cache Size" : {
          "displayName" : "Cache Value Lookup Cache Size",
          "dynamic" : false,
          "identifiesControllerService" : false,
          "name" : "Cache Value Lookup Cache Size",
          "sensitive" : false
        },
        "Stateful Variables Initial Value" : {
          "displayName" : "Stateful Variables Initial Value",
          "dynamic" : false,
          "identifiesControllerService" : false,
          "name" : "Stateful Variables Initial Value",
          "sensitive" : false
        },
        "uuid" : {
          "displayName" : "uuid",
          "dynamic" : true,
          "identifiesControllerService" : false,
          "name" : "uuid",
          "sensitive" : false
        }
      },
      "retriedRelationships" : [ ],
      "retryCount" : 10,
      "runDurationMillis" : 1000,
      "scheduledState" : "ENABLED",
      "schedulingPeriod" : "0 sec",
      "schedulingStrategy" : "TIMER_DRIVEN",
      "style" : { },
      "type" : "org.apache.nifi.processors.attributes.UpdateAttribute",
      "yieldDuration" : "1 sec"
    }, {
      "autoTerminatedRelationships" : [ ],
      "backoffMechanism" : "PENALIZE_FLOWFILE",
      "bulletinLevel" : "WARN",
      "bundle" : {
        "artifact" : "nifi-update-attribute-nar",
        "group" : "org.apache.nifi",
        "version" : "2.9.0"
      },
      "comments" : "",
      "componentType" : "PROCESSOR",
      "concurrentlySchedulableTaskCount" : 1,
      "executionNode" : "ALL",
      "groupIdentifier" : "flow-contents-group",
      "identifier" : "d418c468-bfb4-3db9-bccd-2252fae2d832",
      "maxBackoffPeriod" : "10 mins",
      "name" : "UpdateAttribute",
      "penaltyDuration" : "30 sec",
      "position" : {
        "x" : -1912.0,
        "y" : -320.0
      },
      "properties" : {
        "Store State" : "Do not store state",
        "trace.stop" : "${now()}",
        "Cache Value Lookup Cache Size" : "100"
      },
      "propertyDescriptors" : {
        "Delete Attributes Expression" : {
          "displayName" : "Delete Attributes Expression",
          "dynamic" : false,
          "identifiesControllerService" : false,
          "name" : "Delete Attributes Expression",
          "sensitive" : false
        },
        "Store State" : {
          "displayName" : "Store State",
          "dynamic" : false,
          "identifiesControllerService" : false,
          "name" : "Store State",
          "sensitive" : false
        },
        "trace.stop" : {
          "displayName" : "trace.stop",
          "dynamic" : true,
          "identifiesControllerService" : false,
          "name" : "trace.stop",
          "sensitive" : false
        },
        "Cache Value Lookup Cache Size" : {
          "displayName" : "Cache Value Lookup Cache Size",
          "dynamic" : false,
          "identifiesControllerService" : false,
          "name" : "Cache Value Lookup Cache Size",
          "sensitive" : false
        },
        "Stateful Variables Initial Value" : {
          "displayName" : "Stateful Variables Initial Value",
          "dynamic" : false,
          "identifiesControllerService" : false,
          "name" : "Stateful Variables Initial Value",
          "sensitive" : false
        }
      },
      "retriedRelationships" : [ ],
      "retryCount" : 10,
      "runDurationMillis" : 25,
      "scheduledState" : "ENABLED",
      "schedulingPeriod" : "0 sec",
      "schedulingStrategy" : "TIMER_DRIVEN",
      "style" : { },
      "type" : "org.apache.nifi.processors.attributes.UpdateAttribute",
      "yieldDuration" : "1 sec"
    } ],
    "remoteProcessGroups" : [ ],
    "scheduledState" : "ENABLED",
    "statelessFlowTimeout" : "1 min"
  },
  "flowEncodingVersion" : "1.0",
  "latest" : false,
  "parameterContexts" : { },
  "parameterProviders" : { },
  "snapshotMetadata" : {
    "author" : "admin",
    "flowIdentifier" : "ingest-queue",
    "timestamp" : 1779991747092
  }
}